addons/__init__.py
addons/paired.py
addons/pretrained_transformer_tagger.py
addons/reader_conllcased.py
addons/reader_pandas.py
addons/reader_parallel_classify.py
addons/reporting_xpctl.py
addons/vec_text.py
baseline/__init__.py
baseline/bleu.py
baseline/confusion.py
baseline/conlleval.py
baseline/data.py
baseline/embeddings.py
baseline/mime_type.py
baseline/model.py
baseline/progress.py
baseline/reader.py
baseline/remote.py
baseline/reporting.py
baseline/services.py
baseline/train.py
baseline/utils.py
baseline/vectorizers.py
baseline/version.py
baseline/w2v.py
baseline/onnx/__init__.py
baseline/onnx/remote.py
baseline/onnx/apis/__init__.py
baseline/onnx/apis/grpc_service_pb2.py
baseline/onnx/apis/grpc_service_pb2_grpc.py
baseline/onnx/apis/model_config_pb2.py
baseline/onnx/apis/model_config_pb2_grpc.py
baseline/pytorch/__init__.py
baseline/pytorch/embeddings.py
baseline/pytorch/optz.py
baseline/pytorch/remote.py
baseline/pytorch/torchy.py
baseline/pytorch/classify/__init__.py
baseline/pytorch/classify/model.py
baseline/pytorch/classify/train.py
baseline/pytorch/deps/__init__.py
baseline/pytorch/deps/model.py
baseline/pytorch/deps/train.py
baseline/pytorch/lm/__init__.py
baseline/pytorch/lm/model.py
baseline/pytorch/lm/train.py
baseline/pytorch/seq2seq/__init__.py
baseline/pytorch/seq2seq/decoders.py
baseline/pytorch/seq2seq/encoders.py
baseline/pytorch/seq2seq/model.py
baseline/pytorch/seq2seq/train.py
baseline/pytorch/tagger/__init__.py
baseline/pytorch/tagger/model.py
baseline/pytorch/tagger/train.py
baseline/tensorflow_serving/__init__.py
baseline/tensorflow_serving/apis/__init__.py
baseline/tensorflow_serving/apis/classification_pb2.py
baseline/tensorflow_serving/apis/classification_pb2_grpc.py
baseline/tensorflow_serving/apis/get_model_metadata_pb2.py
baseline/tensorflow_serving/apis/get_model_metadata_pb2_grpc.py
baseline/tensorflow_serving/apis/inference_pb2.py
baseline/tensorflow_serving/apis/inference_pb2_grpc.py
mead_baseline-2.4.2.dist-info/LICENSE
mead_baseline-2.4.2.dist-info/METADATA
mead_baseline-2.4.2.dist-info/NOTICE
mead_baseline-2.4.2.dist-info/WHEEL
mead_baseline-2.4.2.dist-info/entry_points.txt
mead_baseline-2.4.2.dist-info/top_level.txt
mead_baseline-2.4.2.dist-info/RECORD
