Metadata-Version: 2.1
Name: mead-baseline
Version: 2.4.2
Summary: Strong Deep-Learning Baseline algorithms for NLP
Home-page: https://www.github.com/dpressel/baseline
Author: dpressel
Author-email: dpressel@gmail.com
License: Apache 2.0
Download-URL: https://www.github.com/dpressel/baseline/archive/2.4.2.tar.gz
Keywords: deep-learning,nlp,pytorch,tensorflow
Platform: UNKNOWN
Classifier: Development Status :: 3 - Alpha
Classifier: Operating System :: OS Independent
Classifier: Natural Language :: English
Classifier: Topic :: Scientific/Engineering :: Artificial Intelligence
Classifier: Programming Language :: Python :: 3.5
Classifier: Programming Language :: Python :: 3.7
Classifier: Programming Language :: Python :: 3.6
Classifier: Intended Audience :: Developers
Classifier: Intended Audience :: Science/Research
Classifier: License :: OSI Approved :: Apache Software License
Classifier: Environment :: Console
License-File: LICENSE
License-File: NOTICE
Requires-Dist: numpy
Requires-Dist: six
Requires-Dist: mead-layers (==2.4.2)
Provides-Extra: bpe
Requires-Dist: fastBPE ; extra == 'bpe'
Provides-Extra: bpex
Requires-Dist: fastBPE ; extra == 'bpex'
Requires-Dist: subword-nmt ; extra == 'bpex'
Provides-Extra: grpc
Requires-Dist: grpc ; extra == 'grpc'
Provides-Extra: onnx
Requires-Dist: onnxruntime ; extra == 'onnx'
Provides-Extra: regex
Requires-Dist: regex ; extra == 'regex'
Provides-Extra: report
Requires-Dist: tensorboard ; extra == 'report'
Provides-Extra: test
Requires-Dist: pytest ; extra == 'test'
Requires-Dist: mock ; extra == 'test'
Requires-Dist: contextdecorator ; extra == 'test'
Requires-Dist: pytest-forked ; extra == 'test'
Requires-Dist: onnxruntime ; extra == 'test'
Provides-Extra: tf2
Requires-Dist: tensorflow-addons ; extra == 'tf2'
Provides-Extra: tfrecord
Requires-Dist: tfrecord ; extra == 'tfrecord'
Provides-Extra: yaml
Requires-Dist: pyyaml ; extra == 'yaml'
